ibis/__init__.py
ibis/backends/__init__.py
ibis/backends/base/__init__.py
ibis/backends/base/df/__init__.py
ibis/backends/base/df/scope.py
ibis/backends/base/df/timecontext.py
ibis/backends/base/sql/__init__.py
ibis/backends/base/sql/alchemy/__init__.py
ibis/backends/base/sql/alchemy/datatypes.py
ibis/backends/base/sql/alchemy/geospatial.py
ibis/backends/base/sql/alchemy/query_builder.py
ibis/backends/base/sql/alchemy/registry.py
ibis/backends/base/sql/alchemy/translator.py
ibis/backends/base/sql/compiler/__init__.py
ibis/backends/base/sql/compiler/base.py
ibis/backends/base/sql/compiler/query_builder.py
ibis/backends/base/sql/compiler/select_builder.py
ibis/backends/base/sql/compiler/translator.py
ibis/backends/base/sql/ddl.py
ibis/backends/base/sql/registry/__init__.py
ibis/backends/base/sql/registry/aggregate.py
ibis/backends/base/sql/registry/binary_infix.py
ibis/backends/base/sql/registry/case.py
ibis/backends/base/sql/registry/geospatial.py
ibis/backends/base/sql/registry/helpers.py
ibis/backends/base/sql/registry/identifiers.py
ibis/backends/base/sql/registry/literal.py
ibis/backends/base/sql/registry/main.py
ibis/backends/base/sql/registry/string.py
ibis/backends/base/sql/registry/timestamp.py
ibis/backends/base/sql/registry/window.py
ibis/backends/base/sqlglot/__init__.py
ibis/backends/base/sqlglot/datatypes.py
ibis/backends/base/sqlglot/tests/__init__.py
ibis/backends/base/sqlglot/tests/test_datatypes.py
ibis/backends/bigquery/__init__.py
ibis/backends/bigquery/client.py
ibis/backends/bigquery/compiler.py
ibis/backends/bigquery/custom_udfs.py
ibis/backends/bigquery/datatypes.py
ibis/backends/bigquery/operations.py
ibis/backends/bigquery/registry.py
ibis/backends/bigquery/rewrites.py
ibis/backends/bigquery/tests/__init__.py
ibis/backends/bigquery/tests/conftest.py
ibis/backends/bigquery/tests/system/__init__.py
ibis/backends/bigquery/tests/system/conftest.py
ibis/backends/bigquery/tests/system/snapshots/test_client/test_cross_project_query/out.sql
ibis_framework-7.0.0.dist-info/LICENSE.txt
ibis_framework-7.0.0.dist-info/METADATA
ibis_framework-7.0.0.dist-info/WHEEL
ibis_framework-7.0.0.dist-info/entry_points.txt
ibis_framework-7.0.0.dist-info/RECORD
