Metadata-Version: 2.1
Name: ibis-framework
Version: 7.0.0
Summary: Productivity-centric Python Big Data Framework
Home-page: https://ibis-project.org
License: Apache-2.0
Author: Ibis Maintainers
Author-email: maintainers@ibis-project.org
Maintainer: Ibis Maintainers
Maintainer-email: maintainers@ibis-project.org
Requires-Python: >=3.9,<4.0
Classifier: Development Status :: 5 - Production/Stable
Classifier: Intended Audience :: Science/Research
Classifier: License :: OSI Approved :: Apache Software License
Classifier: Operating System :: OS Independent
Classifier: Programming Language :: Python
Classifier: Programming Language :: Python :: 3
Classifier: Programming Language :: Python :: 3.9
Classifier: Programming Language :: Python :: 3.10
Classifier: Programming Language :: Python :: 3.11
Classifier: Topic :: Scientific/Engineering
Provides-Extra: all
Provides-Extra: bigquery
Provides-Extra: clickhouse
Provides-Extra: dask
Provides-Extra: datafusion
Provides-Extra: decompiler
Provides-Extra: deltalake
Provides-Extra: druid
Provides-Extra: duckdb
Provides-Extra: flink
Provides-Extra: geospatial
Provides-Extra: impala
Provides-Extra: mssql
Provides-Extra: mysql
Provides-Extra: oracle
Provides-Extra: pandas
Provides-Extra: polars
Provides-Extra: postgres
Provides-Extra: pyspark
Provides-Extra: snowflake
Provides-Extra: sqlite
Provides-Extra: trino
Provides-Extra: visualization
Requires-Dist: GeoAlchemy2 (>=0.6.3,<1,!=0.13.0,!=0.14.0,!=0.14.1) ; extra == "all" or extra == "geospatial"
Requires-Dist: atpublic (>=2.3,<5)
Requires-Dist: bidict (>=0.22.1,<1)
Requires-Dist: black (>=22.1.0,<24) ; extra == "all" or extra == "decompiler"
Requires-Dist: clickhouse-connect[arrow,numpy,pandas] (>=0.5.23,<1) ; extra == "all" or extra == "clickhouse"
Requires-Dist: dask[array,dataframe] (>=2022.9.1) ; extra == "all" or extra == "dask"
Requires-Dist: datafusion (>=0.6,<32) ; extra == "all" or extra == "datafusion"
Requires-Dist: db-dtypes (>=0.3,<2) ; extra == "all" or extra == "bigquery"
Requires-Dist: deltalake (>=0.9.0,<1) ; extra == "all" or extra == "deltalake"
Requires-Dist: duckdb (>=0.8.1,<1) ; extra == "all" or extra == "duckdb"
Requires-Dist: duckdb-engine (>=0.1.8,<1) ; extra == "all" or extra == "duckdb"
Requires-Dist: filelock (>=3.7.0,<4)
Requires-Dist: fsspec (>=2022.1.0) ; extra == "all" or extra == "impala"
Requires-Dist: geopandas (>=0.6,<1) ; extra == "all" or extra == "geospatial"
Requires-Dist: google-cloud-bigquery (>=3,<4) ; extra == "all" or extra == "bigquery"
Requires-Dist: google-cloud-bigquery-storage (>=2,<3) ; extra == "all" or extra == "bigquery"
Requires-Dist: graphviz (>=0.16,<1) ; extra == "all" or extra == "visualization"
Requires-Dist: impyla (>=0.17,<1) ; extra == "all" or extra == "impala"
Requires-Dist: multipledispatch (>=0.6,<2)
Requires-Dist: numpy (>=1,<2)
Requires-Dist: oracledb (>=1.3.1,<2) ; extra == "all" or extra == "oracle"
Requires-Dist: packaging (>=21.3,<24) ; extra == "all" or extra == "oracle"
Requires-Dist: pandas (>=1.2.5,<3)
Requires-Dist: parsy (>=2,<3)
Requires-Dist: pins[gcs] (>=0.8.2,<1)
Requires-Dist: polars (>=0.19,<1) ; extra == "all" or extra == "polars"
Requires-Dist: psycopg2 (>=2.8.4,<3) ; extra == "all" or extra == "postgres"
Requires-Dist: pyarrow (>=2,<14)
Requires-Dist: pydata-google-auth (>=1.4.0,<2) ; extra == "all" or extra == "bigquery"
Requires-Dist: pydruid[sqlalchemy] (>=0.6.5,<1) ; extra == "all" or extra == "druid"
Requires-Dist: pymssql (>=2.2.5,<3) ; extra == "all" or extra == "mssql"
Requires-Dist: pymysql (>=1,<2) ; extra == "all" or extra == "mysql"
Requires-Dist: pyspark (>=3,<4) ; extra == "all" or extra == "pyspark"
Requires-Dist: python-dateutil (>=2.8.2,<3)
Requires-Dist: pytz (>=2022.7)
Requires-Dist: regex (>=2021.7.6) ; extra == "all" or extra == "dask" or extra == "pandas" or extra == "sqlite"
Requires-Dist: requests (>=2,<3) ; extra == "all" or extra == "impala"
Requires-Dist: rich (>=12.4.4,<14)
Requires-Dist: shapely (>=2,<3) ; extra == "all" or extra == "geospatial"
Requires-Dist: snowflake-connector-python[pandas] (>=3.0.2,<4,!=3.3.0b1) ; extra == "all" or extra == "snowflake"
Requires-Dist: snowflake-sqlalchemy[pandas] (>=1.4.1,<2) ; extra == "all" or extra == "snowflake"
Requires-Dist: sqlalchemy (>=1.4,<3) ; extra == "all" or extra == "clickhouse" or extra == "druid" or extra == "duckdb" or extra == "impala" or extra == "mssql" or extra == "mysql" or extra == "oracle" or extra == "postgres" or extra == "pyspark" or extra == "sqlite" or extra == "trino"
Requires-Dist: sqlalchemy-views (>=0.3.1,<1) ; extra == "all" or extra == "duckdb" or extra == "mssql" or extra == "mysql" or extra == "oracle" or extra == "postgres" or extra == "snowflake" or extra == "sqlite" or extra == "trino"
Requires-Dist: sqlglot (>=18.7.0,<19)
Requires-Dist: toolz (>=0.11,<1)
Requires-Dist: trino[sqlalchemy] (>=0.321,<1) ; extra == "all" or extra == "trino"
Requires-Dist: typing-extensions (>=4.3.0,<5)
Project-URL: Documentation, https://ibis-project.org
Project-URL: Issue Tracker, https://github.com/ibis-project/ibis/issues
Project-URL: Repository, https://github.com/ibis-project/ibis
